process_msg/__init__.py
process_msg/process_msg.py
process_msg-0.0.2.dist-info/METADATA
process_msg-0.0.2.dist-info/WHEEL
process_msg-0.0.2.dist-info/top_level.txt
process_msg-0.0.2.dist-info/RECORD
